openmodule_test/__init__.py
openmodule_test/alert.py
openmodule_test/connection_status.py
openmodule_test/core.py
openmodule_test/database.py
openmodule_test/eventlistener.py
openmodule_test/files.py
openmodule_test/gate.py
openmodule_test/health.py
openmodule_test/interrupt.py
openmodule_test/io_simulator.py
openmodule_test/package_reader.py
openmodule_test/presence.py
openmodule_test/rpc.py
openmodule_test/sentry.py
openmodule_test/settings.py
openmodule_test/signal_simulator.py
openmodule_test/utils.py
openmodule_test/zeromq.py
openmodule_test-16.0.5.dist-info/METADATA
openmodule_test-16.0.5.dist-info/WHEEL
openmodule_test-16.0.5.dist-info/top_level.txt
openmodule_test-16.0.5.dist-info/RECORD
